shapflow/__init__.py
shapflow/flow.py
shapflow/linear_evaluation.py
shapflow/on_manifold.py
shapflow/archive/pseudo_code.py
shapflow/archive/wrap_run.py
shapflow/archive/old_versions/flow0.py
shapflow/archive/old_versions/flow1.py
shapflow/archive/old_versions/flow2.py
shapflow/archive/old_versions/wrap_run.py
shapflow-0.0.1.dist-info/LICENSE
shapflow-0.0.1.dist-info/METADATA
shapflow-0.0.1.dist-info/WHEEL
shapflow-0.0.1.dist-info/top_level.txt
shapflow-0.0.1.dist-info/RECORD
